BelNorm/__init__.py
BelNorm/normalizer.py
BelNorm/splitter.py
belnorm-0.3.0.dist-info/METADATA
belnorm-0.3.0.dist-info/WHEEL
belnorm-0.3.0.dist-info/top_level.txt
belnorm-0.3.0.dist-info/RECORD
