Metadata-Version: 2.4
Name: BelNorm
Version: 0.3.0
Summary: Belarusian text normalizer
Author: Aleś Bułojčyk
Classifier: License :: OSI Approved :: GNU Lesser General Public License v3 or later (LGPLv3+)
Requires-Python: >=3.12
Requires-Dist: stanza
